amazon_kclpy/__init__.py
amazon_kclpy/checkpoint_error.py
amazon_kclpy/dispatch.py
amazon_kclpy/kcl.py
amazon_kclpy/messages.py
amazon_kclpy/jars/__init__.py
amazon_kclpy/jars/amazon-kinesis-client-2.5.8.jar
amazon_kclpy/jars/amazon-kinesis-client-multilang-2.5.8.jar
amazon_kclpy/jars/animal-sniffer-annotations-1.20.jar
amazon_kclpy/jars/annotations-2.25.11.jar
amazon_kclpy/jars/apache-client-2.25.11.jar
amazon_kclpy/jars/arns-2.25.11.jar
amazon_kclpy/jars/auth-2.25.11.jar
amazon_kclpy/jars/aws-cbor-protocol-2.25.11.jar
amazon_kclpy/jars/aws-core-2.25.11.jar
amazon_kclpy/jars/aws-java-sdk-core-1.12.668.jar
amazon_kclpy/jars/aws-java-sdk-sts-1.12.668.jar
amazon_kclpy/jars/aws-json-protocol-2.25.11.jar
amazon_kclpy/jars/aws-query-protocol-2.25.11.jar
amazon_kclpy/jars/checker-qual-2.5.2.jar
amazon_kclpy/jars/checksums-2.25.11.jar
amazon_kclpy/jars/checksums-spi-2.25.11.jar
amazon_kclpy/jars/cloudwatch-2.25.11.jar
amazon_kclpy/jars/commons-beanutils-1.9.4.jar
amazon_kclpy/jars/commons-codec-1.15.jar
amazon_kclpy/jars/commons-collections-3.2.2.jar
amazon_kclpy/jars/commons-collections4-4.2.jar
amazon_kclpy/jars/commons-io-2.11.0.jar
amazon_kclpy/jars/commons-lang3-3.12.0.jar
amazon_kclpy/jars/commons-logging-1.1.3.jar
amazon_kclpy/jars/dynamodb-2.25.11.jar
amazon_kclpy/jars/endpoints-spi-2.25.11.jar
amazon_kclpy/jars/error_prone_annotations-2.7.1.jar
amazon_kclpy/jars/flow-1.7.jar
amazon_kclpy/jars/guava-32.1.1-jre.jar
amazon_kclpy/jars/http-auth-2.25.11.jar
amazon_kclpy/jars/http-auth-aws-2.25.11.jar
amazon_kclpy/jars/http-auth-spi-2.25.11.jar
amazon_kclpy/jars/http-client-spi-2.25.11.jar
amazon_kclpy/jars/httpclient-4.5.13.jar
amazon_kclpy/jars/httpcore-4.4.15.jar
amazon_kclpy/jars/identity-spi-2.25.11.jar
amazon_kclpy/jars/ion-java-1.11.4.jar
amazon_kclpy/jars/j2objc-annotations-1.3.jar
amazon_kclpy/jars/jackson-annotations-2.13.5.jar
amazon_kclpy/jars/jackson-core-2.13.5.jar
amazon_kclpy/jars/jackson-databind-2.13.5.jar
amazon_kclpy_ekirmayer-2.1.5.dist-info/LICENSE.txt
amazon_kclpy_ekirmayer-2.1.5.dist-info/METADATA
amazon_kclpy_ekirmayer-2.1.5.dist-info/NOTICE.txt
amazon_kclpy_ekirmayer-2.1.5.dist-info/WHEEL
amazon_kclpy_ekirmayer-2.1.5.dist-info/top_level.txt
amazon_kclpy_ekirmayer-2.1.5.dist-info/RECORD
